{
	"landing": {
		"title": "Bonjour,\nje suis Baptiste Dauphouy,\ndéveloppeur full-stack.",
		"badges": [
			{
				"handle": "available",
				"title": "Disponible"
			},
			{
				"handle": "unavailable",
				"title": "Non disponible"
			},
			{
				"handle": "location",
				"title": "Valencia, Espagne"
			}
		]
	},
	"resume": {
		"title": "Télécharger mon CV"
	},
	"projects": [
		{
			"handle": "shopiette",
			"description": "Créez rapidement des sites e-commerce avec Svelte.",
			"badges": [
				{
					"handle": "in-progress",
					"title": "En cours"
				}
			],
			"links": [
				{
					"handle": "github",
					"title": "Voir le Github"
				},
				{
					"handle": "website",
					"title": "Voir le site"
				}
			]
		},
		{
			"handle": "vintify",
			"description": "Importez facilement vos produits Vinted sur Shopify.",
			"links": [
				{
					"handle": "github",
					"title": "Voir le Github"
				},
				{
					"handle": "website",
					"title": "Voir le site"
				}
			]
		},
		{
			"handle": "vitaliplay",
			"description": "Vitaliplay est une plateforme sportive pour les seniors.",
			"links": [
				{
					"handle": "github",
					"title": "Voir le Github"
				},
				{
					"handle": "website",
					"title": "Voir le site"
				}
			]
		}
	],
	"timeline": {
		"technologiesTitle": "Technologies utilisées",
		"membersTitle": "Membres du projet",
		"items": [
			{
				"date": "01/01/2018",
				"title": "janvier 2018",
				"text": "Découverte de la programmation avec Scratch.",
				"technologies": ["Scratch"],
				"members": [
					{
						"name": "Arthur",
						"link": "https://arthurfontaine.fr"
					},
					{
						"name": "Thierry",
						"link": "https://tmgn.me"
					}
				]
			},
			{
				"date": "01/06/2018",
				"title": "juin 2018",
				"text": "Présentation de mon jeu qui me fait obtenir la note de 16/20 à l'oral du brevet.",
				"technologies": ["Scratch"]
			},
			{
				"date": "01/09/2018",
				"title": "septembre 2018",
				"text": "Découverte de l'HTML et du CSS au lycée.",
				"technologies": ["HTML", "CSS"]
			}
		]
	},
	"contact": {
		"title": "Contact",
		"subtitle": "Pour toute demande me concernant, vous pouvez me contacter par e-mail ou via mes réseaux sociaux."
	},
	"footer": {
		"text": "Fait avec Svelte et amour par Baptiste Dauphouy."
	}
}
